{
  "kind": "collectionType",
  "collectionName": "comments",
  "info": {
    "singularName": "comment",
    "pluralName": "comments",
    "displayName": "Comments",
    "description": ""
  },
  "options": {
    "draftAndPublish": true
  },
  "pluginOptions": {
    "i18n": {
      "localized": true
    }
  },
  "attributes": {
    "name": {
      "type": "string",
      "pluginOptions": {
        "i18n": {
          "localized": true
        }
      },
      "required": true
    },
    "text": {
      "type": "text",
      "required": true,
      "pluginOptions": {
        "i18n": {
          "localized": true
        }
      }
    },
    "instagram": {
      "type": "string"
    },
    "result": {
      "type": "string"
    },
    "img": {
      "type": "media",
      "multiple": false,
      "required": false,
      "allowedTypes": [
        "images",
        "files",
        "videos",
        "audios"
      ]
    }
  }
}
